README.md
setup.cfg
setup.py
py_gd/__init__.py
py_gd/gd_enum.py
py_gd/google_drive.py
py_gd.egg-info/PKG-INFO
py_gd.egg-info/SOURCES.txt
py_gd.egg-info/dependency_links.txt
py_gd.egg-info/requires.txt
py_gd.egg-info/top_level.txt