Metadata-Version: 2.1
Name: py-gd
Version: 0.0.2
Summary: A tiny package for Google Drive
Home-page: https://github.com/kilfu0701/py-gd
Author: BoRu Su
Author-email: kilfu0701@gmail.com
License: UNKNOWN
Platform: UNKNOWN
Classifier: Programming Language :: Python :: 3.6
Classifier: Programming Language :: Python :: 3.7
Classifier: License :: OSI Approved :: MIT License
Classifier: Operating System :: OS Independent
